cognee_community_hybrid_adapter_duckdb/__init__.py
cognee_community_hybrid_adapter_duckdb/duckdb_adapter.py
cognee_community_hybrid_adapter_duckdb/register.py
cognee_community_hybrid_adapter_duckdb-0.1.1.dist-info/METADATA
cognee_community_hybrid_adapter_duckdb-0.1.1.dist-info/WHEEL
cognee_community_hybrid_adapter_duckdb-0.1.1.dist-info/top_level.txt
cognee_community_hybrid_adapter_duckdb-0.1.1.dist-info/RECORD
