Metadata-Version: 2.4
Name: cognee-community-hybrid-adapter-duckdb
Version: 0.1.1
Summary: DuckDB vector adapter for Cognee with planned graph support
Author-email: Cognee Community <community@cognee.ai>
Maintainer-email: Cognee Community <community@cognee.ai>
License-Expression: Apache-2.0
Project-URL: Homepage, https://github.com/topoteretes/cognee-community
Project-URL: Repository, https://github.com/topoteretes/cognee-community
Project-URL: Issues, https://github.com/topoteretes/cognee-community/issues
Project-URL: Documentation, https://docs.cognee.ai
Project-URL: README, https://github.com/topoteretes/cognee-community/blob/main/packages/hybrid/duckdb/README.md
Keywords: cognee,duckdb,vector,database,embeddings,ai,ml
Classifier: Development Status :: 3 - Alpha
Classifier: Intended Audience :: Developers
Classifier: Operating System :: OS Independent
Classifier: Programming Language :: Python :: 3
Classifier: Programming Language :: Python :: 3.12
Classifier: Programming Language :: Python :: 3.13
Classifier: Topic :: Database
Classifier: Topic :: Scientific/Engineering :: Artificial Intelligence
Classifier: Topic :: Software Development :: Libraries :: Python Modules
Requires-Python: <=3.13,>=3.10
Requires-Dist: cognee>=0.2.4
Requires-Dist: duckdb>=1.3.2
Provides-Extra: dev
Requires-Dist: mypy>=1.17.1; extra == "dev"
Requires-Dist: twine>=5.0.0; extra == "dev"
Requires-Dist: build>=1.0.0; extra == "dev"
